userbot/__init__.py
userbot/__main__.py
userbot/config.py
userbot/events.py
userbot/prettyjson.py
userbot/util.py
userbot/utils.py
userbot/helpers/__init__.py
userbot/helpers/fonts.py
userbot/helpers/functions.py
userbot/helpers/funts.py
userbot/helpers/memeifyhelpers.py
userbot/helpers/progress.py
userbot/helpers/qhelper.py
userbot/helpers/resources/__init__.py
userbot/helpers/resources/states.py
userbot/helpers/styles/__init__.py
userbot/javes_main/__init__.py
userbot/javes_main/commands.py
userbot/javes_main/heroku_var.py
userbot/javes_main/extra/__init__.py
userbot/javes_main/extra/google_images_download.py
userbot-0.0.4.dist-info/LICENSE
userbot-0.0.4.dist-info/METADATA
userbot-0.0.4.dist-info/WHEEL
userbot-0.0.4.dist-info/top_level.txt
userbot-0.0.4.dist-info/RECORD
